.coveragerc
.flake8
.pre-commit-config.yaml
.readthedocs.yml
.travis.yml
CHANGES.rst
LICENSE
README.rst
appveyor.yml
azure-pipelines.yml
conftest.py
pyproject.toml
pytest.ini
setup.cfg
setup.py
skeleton.md
tox.ini
docs/conf.py
docs/history.rst
docs/index.rst
wolframalpha/__init__.py
wolframalpha/pmxbot.py
wolframalpha/test_client.py
wolframalpha/test_pmxbot.py
wolframalphaforked.egg-info/PKG-INFO
wolframalphaforked.egg-info/SOURCES.txt
wolframalphaforked.egg-info/dependency_links.txt
wolframalphaforked.egg-info/entry_points.txt
wolframalphaforked.egg-info/requires.txt
wolframalphaforked.egg-info/top_level.txt