Metadata-Version: 2.1
Name: wolframalphaforked
Version: 4.0.2
Summary: Wolfram|Alpha 2.0 API client
Home-page: https://github.com/federicotorrielli/wolframalpha
Author: Jason R. Coombs and Federico Torrielli
Author-email: evilscript@protonmail.com
License: UNKNOWN
Platform: UNKNOWN
Classifier: Development Status :: 5 - Production/Stable
Classifier: Intended Audience :: Developers
Classifier: License :: OSI Approved :: MIT License
Classifier: Programming Language :: Python :: 3
Classifier: Programming Language :: Python :: 3 :: Only
Requires-Python: >=3.6
Provides-Extra: testing
Provides-Extra: docs
